palitra/__init__.py
palitra/_core.py
palitra/_global.py
palitra/py.typed
palitra-0.0.1.post1.dist-info/licenses/LICENSE
palitra-0.0.1.post1.dist-info/METADATA
palitra-0.0.1.post1.dist-info/WHEEL
palitra-0.0.1.post1.dist-info/top_level.txt
palitra-0.0.1.post1.dist-info/RECORD
