Metadata-Version: 2.4
Name: palitra
Version: 0.0.1.post1
Summary: Run async functions seamlessly from sync code using a persistent background event loop.
Author-email: Albert Namaev <anamaev263@gmail.com>
Maintainer-email: Albert Namaev <anamaev263@gmail.com>
License: BSD-3-Clause
Project-URL: Homepage, https://github.com/abebus/palitra
Project-URL: Repository, https://github.com/abebus/palitra
Project-URL: Documentation, https://github.com/abebus/palitra/tree/main/docs
Keywords: asyncio,async,event loop,concurrency
Classifier: Development Status :: 3 - Alpha
Classifier: Intended Audience :: Developers
Classifier: License :: OSI Approved :: BSD License
Classifier: Operating System :: OS Independent
Classifier: Programming Language :: Python
Classifier: Programming Language :: Python :: 3
Classifier: Programming Language :: Python :: 3.9
Classifier: Programming Language :: Python :: 3.10
Classifier: Programming Language :: Python :: 3.11
Classifier: Programming Language :: Python :: 3.12
Classifier: Programming Language :: Python :: 3.13
Classifier: Programming Language :: Python :: 3.14
Classifier: Topic :: Software Development :: Libraries :: Python Modules
Classifier: Topic :: System :: Operating System
Classifier: Topic :: Utilities
Classifier: Typing :: Typed
Classifier: Framework :: AsyncIO
Classifier: Operating System :: POSIX
Classifier: Operating System :: Microsoft :: Windows
Requires-Python: >=3.9
License-File: LICENSE
Requires-Dist: typing_extensions>=4.0.0; python_version < "3.10"
Dynamic: license-file
